vindta_reCAlk/__init__.py
vindta_reCAlk/__main__.py
vindta_reCAlk/calcs.py
vindta_reCAlk/defaults.py
vindta_reCAlk/views.py
vindta_reCAlk/static/css/bootstrap.min.css
vindta_reCAlk/static/css/fontawesome.min.css
vindta_reCAlk/static/css/user.css
vindta_reCAlk/static/img/README.md
vindta_reCAlk/static/js/app_sockets.js
vindta_reCAlk/static/js/bootstrap.min.js
vindta_reCAlk/static/js/jquery-3.2.1.min.js
vindta_reCAlk/templates/index.html
vindta_reCAlk-0.2.4.dist-info/LICENSE
vindta_reCAlk-0.2.4.dist-info/METADATA
vindta_reCAlk-0.2.4.dist-info/WHEEL
vindta_reCAlk-0.2.4.dist-info/entry_points.txt
vindta_reCAlk-0.2.4.dist-info/top_level.txt
vindta_reCAlk-0.2.4.dist-info/RECORD
