Metadata-Version: 2.1
Name: vindta-reCAlk
Version: 0.2.4
Summary: Recalculate VINDTA 3C TA and DIC from CRMs
Home-page: http://luke-gregor.github.io
Author: Luke Gregor
Author-email: lukegre@gmail.com
License: MIT License
Platform: UNKNOWN
Requires-Dist: Flask
Requires-Dist: requires
Requires-Dist: numpy
Requires-Dist: scipy
Requires-Dist: pandas
Requires-Dist: openpyxl
Requires-Dist: xlrd
